LICENSE
README.md
setup.py
31.egg-info/PKG-INFO
31.egg-info/SOURCES.txt
31.egg-info/dependency_links.txt
31.egg-info/entry_points.txt
31.egg-info/requires.txt
31.egg-info/top_level.txt
s31/__init__.py
s31/active_process_table.py
s31/command.py
s31/config.py
s31/foreach.py
s31/interruptable_runner.py
s31/mail.py
s31/main.py
s31/notify.py
s31/process_manager.py
s31/screen.py
s31/utils.py
s31/workers.py
tests/__init__.py
tests/basic_test.py
tests/buf_test.py
tests/duplicate_names_test.py
tests/foreach_test.py
tests/options_test.py
tests/test31.py
tests/workers_test.py