Metadata-Version: 2.4
Name: 31
Version: 2.3.0
Summary: Runs code in a specified environment in the background and notifies you when it is done.
Home-page: https://github.com/kavigupta/31
Author: Kavi Gupta
Author-email: 31@kavigupta.org
Classifier: Programming Language :: Python :: 3.5
Classifier: Programming Language :: Python :: 3.6
Classifier: Programming Language :: Python :: 3.7
Classifier: Programming Language :: Python :: 3.8
Classifier: Operating System :: OS Independent
Requires-Python: >=3.5
License-File: LICENSE
Requires-Dist: attrs>=20.1.0
Requires-Dist: display-timedelta==1.1
Requires-Dist: filelock==3.0.12
Requires-Dist: appdirs>=1.4.4
Requires-Dist: permacache>=3.6.1
Dynamic: author
Dynamic: author-email
Dynamic: classifier
Dynamic: description
Dynamic: description-content-type
Dynamic: home-page
Dynamic: license-file
Dynamic: requires-dist
Dynamic: requires-python
Dynamic: summary
